pyalphashape/AlphaShape.py
pyalphashape/GraphClosure.py
pyalphashape/SphereCap.py
pyalphashape/SphericalAlphaShape.py
pyalphashape/SphericalDelaunay.py
pyalphashape/__init__.py
pyalphashape/plotting.py
pyalphashape/sphere_utils.py
pyalphashape-0.1.0.dist-info/LICENSE
pyalphashape-0.1.0.dist-info/METADATA
pyalphashape-0.1.0.dist-info/WHEEL
pyalphashape-0.1.0.dist-info/RECORD
