Metadata-Version: 2.3
Name: pyalphashape
Version: 0.1.0
Summary: A Python library for Alpha Shapes in Euclidean and Spherical Geometries.
License: MIT
Keywords: AlphaShape,Alpha Shape,Convex Hull,Spherical,Geometry
Author: Niklas M. Melton
Author-email: niklasmelton@gmail.com
Requires-Python: >=3.9,<4.0
Classifier: Development Status :: 3 - Alpha
Classifier: Intended Audience :: Developers
Classifier: Intended Audience :: Science/Research
Classifier: License :: OSI Approved :: MIT License
Classifier: Operating System :: OS Independent
Classifier: Programming Language :: Python :: 3
Classifier: Programming Language :: Python :: 3.9
Classifier: Programming Language :: Python :: 3.10
Classifier: Programming Language :: Python :: 3.11
Classifier: Programming Language :: Python :: 3.12
Classifier: Programming Language :: Python :: 3.13
Classifier: Topic :: Scientific/Engineering :: Mathematics
Requires-Dist: matplotlib (>=3.3.3)
Requires-Dist: numpy (>=1.19.4)
Requires-Dist: plotly (>=5.0.0)
Requires-Dist: scipy (>=1.5.4)
Project-URL: Documentation, https://github.com/NiklasMelton/PyAlphaShape
Project-URL: Homepage, https://github.com/NiklasMelton/PyAlphaShape
Project-URL: Repository, https://github.com/NiklasMelton/PyAlphaShape
